{
  "resourceType" : "Observation",
  "id" : "HivTest",
  "meta" : {
    "profile" : ["http://smart.who.int/hiv/StructureDefinition/HivTest"]
  },
  "text" : {
    "status" : "generated",
    "div" : "<div xmlns=\"http://www.w3.org/1999/xhtml\"><p class=\"res-header-id\"><b>Generated Narrative: Observation HivTest</b></p><a name=\"HivTest\"> </a><a name=\"hcHivTest\"> </a><a name=\"HivTest-en-US\"> </a><p><b>status</b>: Final</p><p><b>category</b>: <span title=\"Codes:{http://terminology.hl7.org/CodeSystem/observation-category laboratory}\">Laboratory</span></p><p><b>code</b>: <span title=\"Codes:{http://smart.who.int/hiv/CodeSystem/HIVConcepts HIV.B.DE81}\">HIV Test</span></p><p><b>subject</b>: <a href=\"Patient-example-hiv-patient.html\">Anonymous Patient (no stated gender), DoB Unknown</a></p><p><b>effective</b>: 2023-01-01 14:30:00+0000</p><p><b>issued</b>: 2023-01-03 15:00:00+0000</p><p><b>value</b>: <span title=\"Codes:{http://smart.who.int/hiv/CodeSystem/HIVConcepts HIV.B.DE112}\">HIV-positive</span></p></div>"
  },
  "status" : "final",
  "category" : [{
    "coding" : [{
      "system" : "http://terminology.hl7.org/CodeSystem/observation-category",
      "code" : "laboratory"
    }]
  }],
  "code" : {
    "coding" : [{
      "system" : "http://smart.who.int/hiv/CodeSystem/HIVConcepts",
      "code" : "HIV.B.DE81",
      "display" : "HIV Test"
    }]
  },
  "subject" : {
    "reference" : "Patient/example-hiv-patient"
  },
  "effectiveDateTime" : "2023-01-01T14:30:00Z",
  "issued" : "2023-01-03T15:00:00Z",
  "valueCodeableConcept" : {
    "coding" : [{
      "system" : "http://smart.who.int/hiv/CodeSystem/HIVConcepts",
      "code" : "HIV.B.DE112",
      "display" : "HIV-positive"
    }]
  }
}